NoJoy_DI
