Metadata-Version: 1.1
Name: NoJoy-DI
Version: 0.9.3
Summary: A simple and feature full Dependency Injector for python
Home-page: https://github.com/joyider/NoJoy_DI
Author: Andre Karlsson
Author-email: andre@sess.se
License: GPLv3
Keywords: DI dependency injection ioc
Platform: UNKNOWN
Classifier: Development Status :: 4 - Beta
Classifier: Topic :: Software Development :: Libraries
Classifier: License :: OSI Approved :: GNU General Public License v3 or later (GPLv3+)
Classifier: Programming Language :: Python
Classifier: Programming Language :: Python :: 2.7
Classifier: Programming Language :: Python :: 3.3
Classifier: Programming Language :: Python :: 3.4
Classifier: Programming Language :: Python :: 3.5
